dicom_factory/__init__.py
dicom_factory/factory.py
dicom_factory/validator.py
dicom_factory-0.0.3.dist-info/LICENSE
dicom_factory-0.0.3.dist-info/METADATA
dicom_factory-0.0.3.dist-info/WHEEL
dicom_factory-0.0.3.dist-info/top_level.txt
dicom_factory-0.0.3.dist-info/RECORD
