Metadata-Version: 2.1
Name: dicom-factory
Version: 0.0.3
Summary: DICOM data generator for (mainly) testing purposes
Home-page: https://github.com/jdecid/DICOM-Factory
Author: Josep de Cid
Author-email: josep.de.cid@gmail.com
License: UNKNOWN
Platform: UNKNOWN
Classifier: Programming Language :: Python :: 3
Classifier: License :: OSI Approved :: MIT License
Classifier: Operating System :: OS Independent
Requires-Python: >=3.6
